djf_surveys/__init__.py
djf_surveys/admin.py
djf_surveys/app_settings.py
djf_surveys/apps.py
djf_surveys/context_processors.py
djf_surveys/forms.py
djf_surveys/mixin.py
djf_surveys/models.py
djf_surveys/summary.py
djf_surveys/tests.py
djf_surveys/urls.py
djf_surveys/utils.py
djf_surveys/validators.py
djf_surveys/views.py
djf_surveys/widgets.py
djf_surveys/admins/__init__.py
djf_surveys/admins/urls.py
djf_surveys/admins/views.py
djf_surveys/admins/v2/__init__.py
djf_surveys/admins/v2/forms.py
djf_surveys/admins/v2/views.py
djf_surveys/locale/en/LC_MESSAGES/django.mo
djf_surveys/locale/fr/LC_MESSAGES/django.mo
djf_surveys/locale/id/LC_MESSAGES/django.mo
djf_surveys/migrations/0001_initial.py
djf_surveys/migrations/0002_auto_20220330_1033.py
djf_surveys/migrations/0003_auto_20220330_1036.py
djf_surveys/migrations/0004_auto_20220330_1112.py
djf_surveys/migrations/0005_auto_20220404_1518.py
djf_surveys/migrations/0006_survey_private_response.py
djf_surveys/migrations/0007_auto_20220525_1126.py
djf_surveys/migrations/0008_auto_20220721_0935.py
djf_surveys/migrations/0009_auto_20220803_0927.py
djf_surveys/migrations/0010_model_translation.py
djf_surveys/migrations/0011_alter_question_key.py
djf_surveys/migrations/0012_survey_notification_to.py
djf_surveys/migrations/0013_survey_success_page_content.py
djf_surveys/migrations/0014_alter_survey_success_page_content.py
djf_surveys/migrations/0015_termsvalidators.py
djf_surveys/migrations/0016_alter_survey_description_and_more.py
djf_surveys/migrations/0017_alter_survey_success_page_content.py
djf_surveys/migrations/0018_survey_cycle_survey.py
djf_surveys/migrations/__init__.py
djf_surveys/static/djf_surveys/css/custom.css
djf_surveys/static/djf_surveys/css/rating.css
djf_surveys/static/djf_surveys/css/tailwindcss-3.3.1.js
djf_surveys/static/djf_surveys/css/tailwindcss-plugin-3.3.1.js
djf_surveys/static/djf_surveys/images/star-border.png
djf_surveys/static/djf_surveys/images/star-fill.png
django_form_surveys-2.5.0.dist-info/LICENSE
django_form_surveys-2.5.0.dist-info/METADATA
django_form_surveys-2.5.0.dist-info/WHEEL
django_form_surveys-2.5.0.dist-info/top_level.txt
django_form_surveys-2.5.0.dist-info/RECORD
